django_pg/__init__.py
django_pg/apps.py
django_pg/exceptions.py
django_pg/models.py
django_pg/payment.py
django_pg/signals.py
django_pg/urls.py
django_pg/utils.py
django_pg/views.py
django_pg/flutterwave/__init__.py
django_pg/flutterwave/flutterwave_payment.py
django_pg/interswitch/__init__.py
django_pg/interswitch/interswitch_payment.py
django_pg/paystack/__init__.py
django_pg/paystack/paystack_payment.py
django_pg/stripe/__init__.py
django_pg/stripe/stripe_checkout.py
django_pg/stripe/stripe_payment.py
django_pg/stripe/webhook.py
django_pg-0.5.0.dist-info/LICENCE
django_pg-0.5.0.dist-info/METADATA
django_pg-0.5.0.dist-info/WHEEL
django_pg-0.5.0.dist-info/top_level.txt
django_pg-0.5.0.dist-info/RECORD
