Metadata-Version: 2.1
Name: django-pg
Version: 0.5.0
Summary: Pluggable Django package for integrating multiple payment gateways like Paystack, Flutterwave, Interswitch, Stripe, etc.
Author-email: Adeniyi oluwadamilare <oluwadamilareadeniye@yahoo.com>
License: MIT
Project-URL: Homepage, https://github.com/niyimarc/payment_gateway
Project-URL: Repository, https://github.com/niyimarc/payment_gateway
Project-URL: Issues, https://github.com/niyimarc/payment_gateway/issues
Keywords: django,payment,paystack,flutterwave,stripe,gateway
Classifier: Framework :: Django
Classifier: Programming Language :: Python :: 3
Classifier: Operating System :: OS Independent
Classifier: Intended Audience :: Developers
Classifier: License :: OSI Approved :: MIT License
Classifier: Topic :: Software Development :: Libraries :: Python Modules
Requires-Python: >=3.7
License-File: LICENCE
Requires-Dist: Django >=3.2
Requires-Dist: requests >=2.25
Requires-Dist: stripe >=10.0.0
